{
  "terraform_type": "azurerm_network_manager_network_group",
  "struct_type": "ManagerNetworkGroupResource",
  "namespace": "github.com/hashicorp/terraform-provider-azurerm/internal/services/network",
  "registration_method": "",
  "sdk_type": "modern_sdk",
  "schema_index": "method.ManagerNetworkGroupResource.Arguments.goindex",
  "create_index": "method.ManagerNetworkGroupResource.Create.goindex",
  "read_index": "method.ManagerNetworkGroupResource.Read.goindex",
  "update_index": "method.ManagerNetworkGroupResource.Update.goindex",
  "delete_index": "method.ManagerNetworkGroupResource.Delete.goindex",
  "attribute_index": "method.ManagerNetworkGroupResource.Attributes.goindex"
}