{
  "terraform_type": "azurerm_netapp_volume_quota_rule",
  "struct_type": "NetAppVolumeQuotaRuleResource",
  "namespace": "github.com/hashicorp/terraform-provider-azurerm/internal/services/netapp",
  "registration_method": "",
  "sdk_type": "modern_sdk",
  "schema_index": "method.NetAppVolumeQuotaRuleResource.Arguments.goindex",
  "create_index": "method.NetAppVolumeQuotaRuleResource.Create.goindex",
  "read_index": "method.NetAppVolumeQuotaRuleResource.Read.goindex",
  "update_index": "method.NetAppVolumeQuotaRuleResource.Update.goindex",
  "delete_index": "method.NetAppVolumeQuotaRuleResource.Delete.goindex",
  "attribute_index": "method.NetAppVolumeQuotaRuleResource.Attributes.goindex"
}